pycityvisitorparking/__init__.py
pycityvisitorparking/_version.py
pycityvisitorparking/client.py
pycityvisitorparking/exceptions.py
pycityvisitorparking/models.py
pycityvisitorparking/py.typed
pycityvisitorparking/util.py
pycityvisitorparking/provider/AGENTS.md
pycityvisitorparking/provider/README.md
pycityvisitorparking/provider/__init__.py
pycityvisitorparking/provider/base.py
pycityvisitorparking/provider/loader.py
pycityvisitorparking/provider/manifest.schema.json
pycityvisitorparking/provider/dvsportal/AGENTS.md
pycityvisitorparking/provider/dvsportal/CHANGELOG.md
pycityvisitorparking/provider/dvsportal/README.md
pycityvisitorparking/provider/dvsportal/__init__.py
pycityvisitorparking/provider/dvsportal/api.py
pycityvisitorparking/provider/dvsportal/const.py
pycityvisitorparking/provider/dvsportal/manifest.json
pycityvisitorparking/provider/dvsportal/tests/test_mapping.py
pycityvisitorparking/provider/the_hague/AGENTS.md
pycityvisitorparking/provider/the_hague/CHANGELOG.md
pycityvisitorparking/provider/the_hague/README.md
pycityvisitorparking/provider/the_hague/__init__.py
pycityvisitorparking/provider/the_hague/api.py
pycityvisitorparking/provider/the_hague/const.py
pycityvisitorparking/provider/the_hague/manifest.json
pycityvisitorparking/provider/the_hague/tests/test_mapping.py
pycityvisitorparking-0.5.14.dist-info/METADATA
pycityvisitorparking-0.5.14.dist-info/WHEEL
pycityvisitorparking-0.5.14.dist-info/licenses/LICENSE
pycityvisitorparking-0.5.14.dist-info/RECORD
