Metadata-Version: 2.4
Name: pycityvisitorparking
Version: 0.5.14
Summary: Async integration layer between Home Assistant and Dutch municipal visitor parking APIs.
Project-URL: Homepage, https://github.com/sir-Unknown/pyCityVisitorParking
Project-URL: Repository, https://github.com/sir-Unknown/pyCityVisitorParking
Project-URL: Issues, https://github.com/sir-Unknown/pyCityVisitorParking/issues
Author: pyCityVisitorParking contributors
License: MIT
License-File: LICENSE
Keywords: aiohttp,async,home-assistant,municipality,parking
Classifier: Development Status :: 3 - Alpha
Classifier: Framework :: AsyncIO
Classifier: Intended Audience :: Developers
Classifier: License :: OSI Approved :: MIT License
Classifier: Programming Language :: Python :: 3
Classifier: Programming Language :: Python :: 3.13
Classifier: Programming Language :: Python :: Implementation :: CPython
Classifier: Topic :: Home Automation
Requires-Python: >=3.13
Requires-Dist: aiohttp>=3.9
Provides-Extra: dev
Requires-Dist: build==1.3.0; extra == 'dev'
Requires-Dist: hatch==1.16.2; extra == 'dev'
Requires-Dist: jsonschema==4.25.1; extra == 'dev'
Requires-Dist: pre-commit==4.5.1; extra == 'dev'
Requires-Dist: pyright==1.1.407; extra == 'dev'
Requires-Dist: pytest-asyncio==1.3.0; extra == 'dev'
Requires-Dist: pytest-cov==5.0.0; extra == 'dev'
Requires-Dist: pytest==9.0.2; extra == 'dev'
Requires-Dist: ruff==0.14.10; extra == 'dev'
Requires-Dist: twine==6.2.0; extra == 'dev'
